Workbook

Sheet Backlog
A1: ID | B1: Item | C1: Type | D1: Area | E1: Priority | F1: Est. (days) | G1: Week | H1: Owner | I1: Blocked by | J1: Status | K1: Notes
A2: B1 | B2: Admin view renders for non-admin users | C2: Bug | D2: Dashboard / Auth | E2: P0 | F2: 0.5 | G2: Week 1 | H2: Favour | J2: Not started | K2: Access-control defect - verify RLS, not just the render path
A3: B2 | B3: Professional fees calculated at 0.1% instead of 10% | C3: Bug | D3: Budget engine | E3: P0 | F3: 0.5 | G3: Week 1 | H3: Favour | I3: Vanessa alignment (final %) | J3: Not started | K3: Ship as a configurable rate in app_config
A4: B3 | B4: Password reset behaves as auto-login, not a reset | C4: Bug | D4: Auth | E4: P0 | F4: 0.5 | G4: Week 1 | H4: Favour | J4: Not started | K4: Token-based reset with expiry and single use
A5: B4 | B5: Payment recording in a stage redirects to main Payments page | C5: Bug | D5: Payments | E5: P1 | F5: 0.25 | G5: Week 1 | H5: Favour | J5: Not started | K5: Redirect fix only; full in-stage flow is F10
A6: B5 | B6: Certificate emails send from a personal address | C6: Bug | D6: Notifications | E6: P0 | F6: 0.5 | G6: Week 1 | H6: Favour | I6: Verified Resend sender | J6: Not started | K6: Tied to the infrastructure migration already flagged red
A7: B6 | B7: Invitation email language ignores account language | C7: Bug | D7: Notifications / i18n | E7: P1 | F7: 0.5 | G7: Week 1 | H7: Favour | J7: Not started | K7: Resolve locale from recipient account, not sender session
A8: B7 | B8: Help page email link broken; hello@ address invalid | C8: Bug | D8: Support | E8: P1 | F8: 0.25 | G8: Week 1 | H8: Favour | J8: Not started
A9: B8 | B9: Support tickets do not reliably notify admin | C9: Bug | D9: Support | E9: P1 | F9: 1 | G9: Week 3 | H9: Favour | J9: Not started | K9: Notification is the easy half - the 24h window needs a named owner
A10: B9 | B10: Teams screen pricing display incorrect | C10: Bug | D10: Billing UI | E10: P2 | F10: 0.25 | G10: Week 1 | H10: Favour | J10: Not started
A11: B10 | B11: Default 196-day timeline rejected as unrealistic | C11: Bug | D11: Timeline | E11: P1 | F11: 0.5 | G11: Week 4 | H11: Favour | I11: Vanessa alignment | J11: Blocked | K11: Estimate is implementation only, once the rule exists
A12: F1 | B12: Password strength indicator and complexity enforcement | C12: Feature | D12: Auth | E12: P0 | F12: 0.5 | G12: Week 1 | H12: Favour | J12: Not started
A13: F2 | B13: Two-factor authentication | C13: Feature | D13: Auth | E13: P0 | F13: 1.5 | G13: Week 1 | H13: Favour | J13: Not started | K13: Enrolment, login challenge, recovery codes. TOTP over SMS - see Flags
A14: F3 | B14: Project creation branches on new vs ongoing build | C14: Feature | D14: Creation | E14: P0 | F14: 1.5 | G14: Week 2 | H14: Favour | J14: Not started
A15: F4 | B15: Upload existing plans / BoQ on the ongoing-build path | C15: Feature | D15: Creation | E15: P1 | F15: 1 | G15: Week 2 | H15: Favour | J15: Not started | K15: Storage and review state only; no document parsing in v1
A16: F5 | B16: Slide-based step UI for floor details | C16: Feature | D16: Creation | E16: P1 | F16: 1.5 | G16: Week 2 | H16: Favour | J16: Not started | K16: Must make skipping a floor impossible
A17: F6 | B17: Collect phone and home address before plan selection | C17: Feature | D17: Creation | E17: P1 | F17: 0.5 | G17: Week 2 | H17: Favour | J17: Not started | K17: Site location stays out - handled manually at go-live
A18: F7 | B18: Default finishing to Standard | C18: Feature | D18: Creation / Budget | E18: P1 | F18: 0.25 | G18: Week 2 | H18: Favour | J18: Not started | K18: Engine keeps 1.45/1.70 multipliers; not user-selectable at creation
A19: F8 | B19: Declutter project dashboard | C19: Feature | D19: Dashboard | E19: P1 | F19: 1 | G19: Week 3 | H19: Favour | J19: Not started | K19: Remove payment status, stage progress, predicted timeline; keep cost allocation
A20: F9 | B20: Client dashboard cleanup | C20: Feature | D20: Dashboard | E20: P1 | F20: 0.5 | G20: Week 3 | H20: Favour | I20: Philip: cost-allocation conflict | J20: Blocked | K20: Own projects only; remove upload-evidence
A21: F10 | B21: Record payments inside the stage interface | C21: Feature | D21: Payments | E21: P0 | F21: 1.5 | G21: Week 3 | H21: Favour | J21: Not started
A22: F11 | B22: Replace ID upload with payment-name matching | C22: Feature | D22: Verification | E22: P1 | F22: 1 | G22: Week 3 | H22: Favour | I22: SwyChr name-return confirmation | J22: Blocked | K22: Keep the ID path built but dormant, triggered on flag
A23: F12 | B23: Restrict certificates to Jalla Verify tier | C23: Feature | D23: Certificates | E23: P1 | F23: 0.5 | G23: Week 4 | H23: Favour | I23: Philip: already-issued certificates | J23: Blocked
A24: F13 | B24: Rename the Danger section in account settings | C24: Feature | D24: Settings | E24: P3 | F24: 0.1 | G24: Week 1 | H24: Favour | J24: Not started | K24: Suggest 'Close account'
A25: F14 | B25: Admin to on-ground verifier communication for stage approvals | C25: Feature | D25: Admin | E25: P1 | F25: 5 | G25: Week 5 | H25: Favour | J25: Not started | K25: Phase 1 of the comms build - what the Jalla Verify promise depends on
A26: F15 | B26: In-platform communication replacing WhatsApp, incl. video | C26: Feature | D26: Comms | E26: P2 | F26: 20 | G26: Month 2-3 | H26: Favour | J26: Not started
A27: F16 | B27: Payment reporting and bookkeeping integrated with the BoQ | C27: Feature | D27: Reporting | E27: P2 | F27: 20 | G27: Month 2-3 | H27: Favour | J27: Not started
A28: F17 | B28: WhatsApp integration | C28: Feature | D28: Comms | E28: P2 | F28: 1 | G28: Week 4 | H28: Favour | I28: Philip payment link | J28: Blocked | K28: Conflicts with F15 direction - thinnest possible wiring
A29: F18 | B29: Resources section content | C29: Feature | D29: Resources | E29: P3 | F29: 1 | G29: Week 4 | H29: Favour | I29: Vanessa source documents | J29: Blocked | K29: Explicitly low priority
A30: F19 | B30: Professional fee and 5% miscellaneous buffer formula | C30: Feature | D30: Budget engine | E30: P0 | F30: 1 | G30: Week 4 | H30: Favour | I30: Philip/Vanessa alignment meeting | J30: Blocked
A31: F20 | B31: Roofing feature | C31: Shelved | D31: Creation | E31: - | F31: 0 | G31: Unscheduled | H31: Favour | I31: Clarity on presentation | J31: Shelved | K31: Suspended - users confused by current presentation
A32: V1 | B32: Provide official resource documents | C32: Dependency | D32: Resources | E32: P3 | F32: 0 | G32: Unscheduled | H32: Vanessa | J32: Not started | K32: Unblocks F18
A33: V2 | B33: Define the verification standard process | C33: Dependency | D33: Verification | E33: P1 | F33: 0 | G33: Unscheduled | H33: Vanessa | J33: Not started | K33: Unblocks the Jalla Verify approval workflow and F14

Sheet Summary
A1: Groundwork - Beta Feedback Backlog
A2: Source: Beta Testers Feedback Implementation, 3 Sep 2026 (Philip / Favour). Compiled 4 Sep 2026.
A4: Assumption
A5: Dev capacity (days per week, solo) | B5: 5 | C5: Blue = input. Change it and every variance below recalculates.
A7: By type
A8: Type | B8: Items | C8: Dev days
A9: Bug | B9: =COUNTIFS(Backlog!$C$2:$C$33,$A9) -> 10 | C9: =SUMIFS(Backlog!$F$2:$F$33,Backlog!$C$2:$C$33,$A9) -> 4.75
A10: Feature | B10: =COUNTIFS(Backlog!$C$2:$C$33,$A10) -> 19 | C10: =SUMIFS(Backlog!$F$2:$F$33,Backlog!$C$2:$C$33,$A10) -> 59.35
A11: Dependency | B11: =COUNTIFS(Backlog!$C$2:$C$33,$A11) -> 2 | C11: =SUMIFS(Backlog!$F$2:$F$33,Backlog!$C$2:$C$33,$A11) -> 0
A12: Shelved | B12: =COUNTIFS(Backlog!$C$2:$C$33,$A12) -> 1 | C12: =SUMIFS(Backlog!$F$2:$F$33,Backlog!$C$2:$C$33,$A12) -> 0
A13: Total | B13: =SUM(B9:B12) -> 32 | C13: =SUM(C9:C12) -> 64.1
A15: By priority
A16: Priority | B16: Items | C16: Dev days
A17: P0 | B17: =COUNTIFS(Backlog!$E$2:$E$33,$A17) -> 9 | C17: =SUMIFS(Backlog!$F$2:$F$33,Backlog!$E$2:$E$33,$A17) -> 8
A18: P1 | B18: =COUNTIFS(Backlog!$E$2:$E$33,$A18) -> 15 | C18: =SUMIFS(Backlog!$F$2:$F$33,Backlog!$E$2:$E$33,$A18) -> 13.75
A19: P2 | B19: =COUNTIFS(Backlog!$E$2:$E$33,$A19) -> 4 | C19: =SUMIFS(Backlog!$F$2:$F$33,Backlog!$E$2:$E$33,$A19) -> 41.25
A20: P3 | B20: =COUNTIFS(Backlog!$E$2:$E$33,$A20) -> 3 | C20: =SUMIFS(Backlog!$F$2:$F$33,Backlog!$E$2:$E$33,$A20) -> 1.1
A22: Schedule
A23: Week | B23: Items | C23: Dev days | D23: Capacity | E23: Variance
A24: Week 1 | B24: =COUNTIFS(Backlog!$G$2:$G$33,$A24) -> 11 | C24: =SUMIFS(Backlog!$F$2:$F$33,Backlog!$G$2:$G$33,$A24) -> 5.35 | D24: =$B$5 -> 5 | E24: =D24-C24 -> -0.35
A25: Week 2 | B25: =COUNTIFS(Backlog!$G$2:$G$33,$A25) -> 5 | C25: =SUMIFS(Backlog!$F$2:$F$33,Backlog!$G$2:$G$33,$A25) -> 4.75 | D25: =$B$5 -> 5 | E25: =D25-C25 -> 0.25
A26: Week 3 | B26: =COUNTIFS(Backlog!$G$2:$G$33,$A26) -> 5 | C26: =SUMIFS(Backlog!$F$2:$F$33,Backlog!$G$2:$G$33,$A26) -> 5 | D26: =$B$5 -> 5 | E26: =D26-C26 -> 0
A27: Week 4 | B27: =COUNTIFS(Backlog!$G$2:$G$33,$A27) -> 5 | C27: =SUMIFS(Backlog!$F$2:$F$33,Backlog!$G$2:$G$33,$A27) -> 4 | D27: =$B$5 -> 5 | E27: =D27-C27 -> 1
A28: Week 5 | B28: =COUNTIFS(Backlog!$G$2:$G$33,$A28) -> 1 | C28: =SUMIFS(Backlog!$F$2:$F$33,Backlog!$G$2:$G$33,$A28) -> 5 | D28: =$B$5 -> 5 | E28: =D28-C28 -> 0
A29: Month 2-3 | B29: =COUNTIFS(Backlog!$G$2:$G$33,$A29) -> 2 | C29: =SUMIFS(Backlog!$F$2:$F$33,Backlog!$G$2:$G$33,$A29) -> 40
A30: Unscheduled | B30: =COUNTIFS(Backlog!$G$2:$G$33,$A30) -> 3 | C30: =SUMIFS(Backlog!$F$2:$F$33,Backlog!$G$2:$G$33,$A30) -> 0
A31: Total | B31: =SUM(B24:B30) -> 32 | C31: =SUM(C24:C30) -> 64.1
A33: Reality check
A34: Dev days in Philip's one-week cap | C34: =C24 -> 5.35
A35: Dev days in the whole list | C35: =C13 -> 64.1
A36: Dev days excluding the two month-scale builds | C36: =C13-SUMIFS(Backlog!$F$2:$F$33,Backlog!$G$2:$G$33,"Month 2-3") -> 24.1
A37: Weeks to clear everything except those two builds | C37: =(C13-SUMIFS(Backlog!$F$2:$F$33,Backlog!$G$2:$G$33,"Month 2-3"))/$B$5 -> 4.82
A38: Share of items delivered in week 1 | C38: =COUNTIFS(Backlog!$G$2:$G$33,"Week 1")/COUNTA(Backlog!$A$2:$A$33) -> 0.34375
A39: Share of near-term dev days delivered in week 1 (excl. month-scale) | C39: =C24/(C13-SUMIFS(Backlog!$F$2:$F$33,Backlog!$G$2:$G$33,"Month 2-3")) -> 0.2219917
A40: Items blocked on someone else | C40: =COUNTIFS(Backlog!$J$2:$J$33,"Blocked") -> 7
A42: Week 1 is deliberately the trust block: the role leak, the fee maths, the reset flow, the sender address, 2FA.
A43: SwyChr / 'Switcher' is not blocked by anything below week 1 and can start in parallel from week 2.
A44: Estimates are solo-dev days for build + self-test, excluding review cycles and meetings. Source: Favour's own in-call estimates where given (F15, F16), otherwise assigned here.

Sheet Flags
A1: Open questions - need Philip's answer
A2: Four of these block code, not just planning.
A4: # | B4: Flag | C4: Needed by | D4: Detail
A5: 1 | B5: Cost allocation contradiction | C5: Week 3 | D5: The decisions log says retain cost allocation on the project dashboard AND remove it from the client dashboard. Reading it as: keep at project level, remove from the client home view. One line of confirmation needed.
A6: 2 | B6: The one-week cap does not fit the list | C6: Immediate | D6: ~19 dev days outside the month-scale builds; 24 including F14. Either the cap moves or the scope does. The schedule tab is the scope-moves version.
A7: 3 | B7: WhatsApp integration vs replacing WhatsApp | C7: Week 4 | D7: Paying to integrate a channel we have committed to replacing. Recommend the thinnest possible wiring and no further investment.
A8: 4 | B8: Payment-name matching only verifies card payers | C8: Week 3 | D8: Mobile money and bank transfer on the SwyChr rails may return no verified account name - and SwyChr is the fund custodian, so its KYC posture sets the ceiling, not ours. Confirm what name SwyChr returns before removing anything.
A9: 5 | B9: Certificates already issued on Self Verify | C9: Week 4 | D9: Revoke, grandfather, or hide? Revoking is the cleanest incentive and the worst experience.
A10: 6 | B10: 2FA channel | C10: Week 1 | D10: SMS to Nigeria and Cameroon is expensive and unreliable. Recommend TOTP with email fallback.
A11: 7 | B11: Fee change moves every existing quote | C11: Week 1 | D11: 0.1% to 10% plus a 5% buffer shifts displayed totals by ~15% on every project already in the system, beta testers' included. Recalculate or freeze at the quoted figure?
A12: 8 | B12: Timeline logic shape | C12: Week 4 | D12: Is the new timeline a function of floors/footprint/finishing, or a per-project-type table from Vanessa? Different builds.
A13: 9 | B13: The alignment meeting is the critical path | C13: Immediate | D13: Unblocks B2, B10 and F19. If it does not land before day 3 of week 4, those three slip.
